chensukai/__init__.py
chensukai-0.0.3.dist-info/LICENSE
chensukai-0.0.3.dist-info/METADATA
chensukai-0.0.3.dist-info/WHEEL
chensukai-0.0.3.dist-info/top_level.txt
chensukai-0.0.3.dist-info/RECORD
