Metadata-Version: 2.1
Name: chensukai
Version: 0.0.3
Summary: 一个Python库，用于打招呼
Home-page: UNKNOWN
Author: 陈苏恺
License: UNKNOWN
Platform: UNKNOWN
Classifier: Programming Language :: Python :: 3
Classifier: License :: OSI Approved :: MIT License
Classifier: Operating System :: OS Independent
Requires-Python: >=3.6
License-File: LICENSE
